CHANGES.rst
CONTRIBUTORS.rst
MANIFEST.in
README.rst
VERSION
VERSION_SUFFIX
setup.py
docs/LICENSE.GPL
docs/LICENSE.rst
docs/index.rst
src/visaplan/__init__.py
src/visaplan/empty_module.py
src/visaplan.namespace.pkg_resource.egg-info/PKG-INFO
src/visaplan.namespace.pkg_resource.egg-info/SOURCES.txt
src/visaplan.namespace.pkg_resource.egg-info/dependency_links.txt
src/visaplan.namespace.pkg_resource.egg-info/entry_points.txt
src/visaplan.namespace.pkg_resource.egg-info/namespace_packages.txt
src/visaplan.namespace.pkg_resource.egg-info/not-zip-safe
src/visaplan.namespace.pkg_resource.egg-info/requires.txt
src/visaplan.namespace.pkg_resource.egg-info/top_level.txt
src/visaplan/plone/__init__.py
src/visaplan/plone/PACKAGE/__init__.py
src/visaplan/plone/PACKAGE/tests/test_doctests.py