Metadata-Version: 2.1
Name: visaplan.namespace.pkg-resource
Version: 1.0.dev2
Summary: Dummy namespace package, pkg_resource style
Home-page: https://pypi.org/project/visaplan.PACKAGE
Author: Tobias Herp
Author-email: tobias.herp@visaplan.com
License: GPL version 2
Platform: UNKNOWN
Classifier: Environment :: Web Environment
Classifier: Framework :: Plone
Classifier: Framework :: Plone :: 4.3
Classifier: Programming Language :: Python
Classifier: Programming Language :: Python :: 2.7
Classifier: Intended Audience :: Developers
Classifier: Natural Language :: English
Classifier: Operating System :: OS Independent
Classifier: License :: OSI Approved :: Apache Software License
Classifier: License :: OSI Approved :: GNU General Public License v2 (GPLv2)
